designs/fsm/fsm_mutant_shallow.v
module fsm (
    input  wire clk,
    input  wire rst_n,
    input  wire start,
    output reg  busy,
    output reg  done
);
    localparam IDLE = 2'd0, RUN = 2'd1, FINISH = 2'd2;
    reg [1:0] state;
    reg [2:0] counter;

    always @(posedge clk) begin
        if (!rst_n) begin
            state   <= IDLE;
            counter <= 3'd0;
            busy    <= 1'b0;
            done    <= 1'b0;
        end else begin
            done <= 1'b0;
            case (state)
                IDLE: begin
                    busy <= 1'b0;
                    if (start) begin
                        state   <= RUN;
                        counter <= 3'd0;
                        busy    <= 1'b1;
                    end
                end
                RUN: begin
                    if (counter == 3'd3) begin  // MUTANT: off-by-one, was 3'd4
                        state <= FINISH;
                    end else begin
                        counter <= counter + 3'd1;
                    end
                end
                FINISH: begin
                    busy <= 1'b0;
                    done <= 1'b1;
                    state <= IDLE;
                end
                default: state <= IDLE;
            endcase
        end
    end
endmodule

designs/fsm/tb_fsm.v
`timescale 1ns/1ps
module tb_fsm;
    reg clk = 0;
    reg rst_n = 0;
    reg start = 0;
    wire busy, done;

    fsm dut (.clk(clk), .rst_n(rst_n), .start(start), .busy(busy), .done(done));

    initial begin
        if ($test$plusargs("vcd")) begin
            $dumpfile("tb_fsm.vcd");
            $dumpvars(0, tb_fsm);
        end
    end

    always #5 clk = ~clk;

    integer errors = 0;

    task check(input cond, input [255:0] msg, input integer cycle);
        begin
            if (!cond) begin
                $display("RTLVERDICT_RESULT: FAIL at cycle %0d: %0s", cycle, msg);
                errors = errors + 1;
                $finish;
            end
        end
    endtask

    integer i;
    initial begin
        repeat (2) @(posedge clk);
        @(negedge clk);
        rst_n = 1;

        // after reset: not busy, not done
        @(negedge clk);
        check(busy == 0 && done == 0, "not idle after reset", 0);

        // start a transaction, expect busy within 1 cycle
        start = 1;
        @(negedge clk);
        start = 0;
        check(busy == 1, "busy not asserted after start", 1);

        // run for up to 10 cycles waiting for done
        for (i = 0; i < 10; i = i + 1) begin
            @(negedge clk);
            if (done) begin
                i = 100; // break
            end
        end
        check(done == 1 || busy == 0, "never completed transaction", 10);

        @(negedge clk);
        check(busy == 0, "busy still asserted after done", 11);

        $display("RTLVERDICT_RESULT: PASS");
        $finish;
    end

    initial begin
        #2000;
        $display("RTLVERDICT_RESULT: FAIL at cycle unknown: timeout, testbench did not finish");
        $finish;
    end
endmodule

designs/fsm/tb_fsm.vcd
$date
	Sat Aug 08 22:43:24 2026
$end
$version
	Icarus Verilog
$end
$timescale
	1ps
$end
$scope module tb_fsm $end
$var wire 1 ! done $end
$var wire 1 " busy $end
$var reg 1 # clk $end
$var reg 1 $ rst_n $end
$var reg 1 % start $end
$var integer 32 & errors [31:0] $end
$var integer 32 ' i [31:0] $end
$scope module dut $end
$var wire 1 # clk $end
$var wire 1 $ rst_n $end
$var wire 1 % start $end
$var parameter 2 ( FINISH $end
$var parameter 2 ) IDLE $end
$var parameter 2 * RUN $end
$var reg 1 " busy $end
$var reg 3 + counter [2:0] $end
$var reg 1 ! done $end
$var reg 2 , state [1:0] $end
$upscope $end
$scope task check $end
$var reg 1 - cond $end
$var reg 256 . msg [255:0] $end
$var integer 32 / cycle [31:0] $end
$upscope $end
$upscope $end
$enddefinitions $end
$comment Show the parameter values. $end
$dumpall
b1 *
b0 )
b10 (
$end
#0
$dumpvars
bx /
bx .
x-
bx ,
bx +
bx '
b0 &
0%
0$
0#
x"
x!
$end
#5000
0!
0"
b0 +
b0 ,
1#
#10000
0#
#15000
1#
#20000
1$
0#
#25000
1#
#30000
1%
b0 /
b110111001101111011101000010000001101001011001000110110001100101001000000110000101100110011101000110010101110010001000000111001001100101011100110110010101110100 .
1-
0#
#35000
1"
b1 ,
1#
#40000
b0 '
b1 /
b110001001110101011100110111100100100000011011100110111101110100001000000110000101110011011100110110010101110010011101000110010101100100001000000110000101100110011101000110010101110010001000000111001101110100011000010111001001110100 .
0%
0#
#45000
b1 +
1#
#50000
b1 '
0#
#55000
b10 +
1#
#60000
b10 '
0#
#65000
b11 +
1#
#70000
b11 '
0#
#75000
b100 +
1#
#80000
b100 '
0#
#85000
b10 ,
1#
#90000
b101 '
0#
#95000
b0 ,
1!
0"
1#
#100000
b1010 /
b11011100110010101110110011001010111001000100000011000110110111101101101011100000110110001100101011101000110010101100100001000000111010001110010011000010110111001110011011000010110001101110100011010010110111101101110 .
b1100101 '
0#
#105000
0!
1#
#110000
b1011 /
b11000100111010101110011011110010010000001110011011101000110100101101100011011000010000001100001011100110111001101100101011100100111010001100101011001000010000001100001011001100111010001100101011100100010000001100100011011110110111001100101 .
0#
